pepredicates/.version
pepredicates/__init__.py
pepredicates/predicates.py
pepredicates/utils.py
pepredicates-0.0.3.dist-info/LICENSE
pepredicates-0.0.3.dist-info/METADATA
pepredicates-0.0.3.dist-info/WHEEL
pepredicates-0.0.3.dist-info/top_level.txt
pepredicates-0.0.3.dist-info/RECORD
