Metadata-Version: 2.1
Name: pepredicates
Version: 0.0.3
Summary: Python package to return source classification probabilities for GW posterior samples
Home-page: https://git.ligo.org/will.farr/pepredicates
Author: Will Farr, Chris Pankow, Charlie Hoy
Author-email: will.far@ligo.org
License: GNU
Download-URL: https://git.ligo.org/will.farr/pepredicates
Platform: UNKNOWN
Classifier: Programming Language :: Python :: 3.5
Classifier: Programming Language :: Python :: 3.6
Requires-Dist: astropy (>=4.0)
Requires-Dist: numpy
Requires-Dist: matplotlib
Requires-Dist: seaborn
